Metadata-Version: 2.1
Name: scribble
Version: 1.0.0
Summary: Allows for persistent storage of dictionary data
Home-page: https://github.com/mikemalinowski/scribble
Author: Mike Malinowski
Author-email: mike@twisted.space
License: UNKNOWN
Keywords: scribble dictionary appdata persistent
Platform: UNKNOWN
Classifier: Programming Language :: Python
Classifier: License :: OSI Approved :: MIT License
Classifier: Operating System :: OS Independent
